Workbook

Sheet Dashboard
F1: Loan - O - Meter | N1: ='Audit Report'!B6 -> 0
A20: Client Information Panel | D20: Total Installments | E20: Previous Installment Number | F20: Current Installment Number | G20: Due Date | H20: Days Left | I20: Installment Amount | J20: Principal Component | K20: Interest Component | L20: Principal Outstanding
D21: ='Information Sheet'!J11 -> 5 | E21: ='Information Sheet'!J12 -> 4 | F21: =Dashboard!E21+1 -> 5 | G21: ='Information Sheet'!J8 -> 46266 | H21: =_xlfn.DAYS('Information Sheet'!J7,'Information Sheet'!J6) -> 288 | I21: ='Repayment Schedule'!H6 -> 200365.16 | J21: =-PPMT('Information Sheet'!D8/'Information Sheet'!E10,Dashboard!F21,'Information Sheet'!D9*'Information Sheet'!E10,'Information Sheet'!J9) -> 185523.3 | K21: =-IPMT('Information Sheet'!D8/'Information Sheet'!E10,Dashboard!F21,'Information Sheet'!D9*'Information Sheet'!E10,'Information Sheet'!J9) -> 14841.864 | L21: =VLOOKUP(F21,'Repayment Schedule'!C5:H212,3,0) -> 136365.16

Sheet Information Sheet
C4: Inputs | I4: Output
C5: Asset | D5: Car | E5: Loan | I5: Loan Status | J5: =IF(J6<J7, "Active", "Unactive") -> Active | AE5: Annual | AF5: 1 | AG5: 12
C6: Asset Value | D6: 1000000 | I6: Todays Date | J6: =TODAY() -> 45978 | AE6: Semi-Annual | AF6: 2 | AG6: 6
C7: Down Payment | D7: 0.2 | I7: Maturity Date | J7: =EDATE(D13,D9*12) -> 46266 | AE7: Quarterly | AF7: 4 | AG7: 3
C8: Loan Rate | D8: 0.08 | I8: Next Due Date | J8: =EDATE(D13,CEILING((J6-D13)/(365/E10),1)*(12/E10)) -> 46266 | AE8: Monthly | AF8: 12 | AG8: 1
C9: Tenure | D9: 5 | E9: Years | I9: Loan Amount | J9: =D6-J10 -> 800000
C10: Frequency | D10: Annual | E10: =VLOOKUP(D10,AE5:AG8,2,0) -> 1 | F10: =VLOOKUP(D10,AE5:AG8,3,0) -> 12 | I10: Down Payment | J10: =D6*D7 -> 200000 | AE10: Loan Amount | AF10: ='Information Sheet'!J9 -> 800000
C11: Type | D11: Arrear | E11: =VLOOKUP(D11,AE14:AF15,2,) -> 0 | I11: Total Installments | J11: =D9*E10 -> 5 | AE11: Principal Outstanding | AF11: =Dashboard!L21 -> 136365.16
C12: Pre-Closure Charges | I12: Installments Paid | J12: =INT((J6-D13)/(365/E10)) -> 4
C13: Loan Date | D13: 44440 | I13: Original
AE14: Arrear | AF14: 0
AE15: Advance | AF15: 1

Sheet Repayment Schedule
C3: Loan Amortization Schedule
C5: Installment No. | D5: Due Date | E5: Principal Outstanding | F5: Interest | G5: Principal | H5: Installment
C6: 1 | D6: =IFERROR(EDATE('Information Sheet'!$D$13,'Information Sheet'!$F$10*'Repayment Schedule'!C6),"") -> 44805 | E6: ='Information Sheet'!J9 -> 800000 | F6: =IFERROR(-IPMT('Information Sheet'!$D$8/'Information Sheet'!$E$10,'Repayment Schedule'!C6,'Information Sheet'!$D$9*'Information Sheet'!$E$10,'Information Sheet'!$J$9),"") -> 64000 | G6: =IFERROR(-PPMT('Information Sheet'!$D$8/'Information Sheet'!$E$10,'Repayment Schedule'!C6,'Information Sheet'!$D$9*'Information Sheet'!$E$10,'Information Sheet'!$J$9),"") -> 136365.16 | H6: =IF(C6="","",-PMT('Information Sheet'!$D$8/'Information Sheet'!$E$10,'Information Sheet'!$D$9*'Information Sheet'!$E$10,'Information Sheet'!$J$9)) -> 200365.16
C7: =IF(C6<'Information Sheet'!$J$11,'Repayment Schedule'!C6+1,"") -> 2 | D7: =IFERROR(EDATE('Information Sheet'!$D$13,'Information Sheet'!$F$10*'Repayment Schedule'!C7),"") -> 45170 | E7: =IFERROR((E6-G7),"") -> 652725.62 | F7: =IFERROR(-IPMT('Information Sheet'!$D$8/'Information Sheet'!$E$10,'Repayment Schedule'!C7,'Information Sheet'!$D$9*'Information Sheet'!$E$10,'Information Sheet'!$J$9),"") -> 53090.787 | G7: =IFERROR(-PPMT('Information Sheet'!$D$8/'Information Sheet'!$E$10,'Repayment Schedule'!C7,'Information Sheet'!$D$9*'Information Sheet'!$E$10,'Information Sheet'!$J$9),"") -> 147274.38 | H7: =IF(C7="","",-PMT('Information Sheet'!$D$8/'Information Sheet'!$E$10,'Information Sheet'!$D$9*'Information Sheet'!$E$10,'Information Sheet'!$J$9)) -> 200365.16
C8: =IF(C7<'Information Sheet'!$J$11,'Repayment Schedule'!C7+1,"") -> 3 | D8: =IFERROR(EDATE('Information Sheet'!$D$13,'Information Sheet'!$F$10*'Repayment Schedule'!C8),"") -> 45536 | E8: =IFERROR((E7-G8),"") -> 493669.3 | F8: =IFERROR(-IPMT('Information Sheet'!$D$8/'Information Sheet'!$E$10,'Repayment Schedule'!C8,'Information Sheet'!$D$9*'Information Sheet'!$E$10,'Information Sheet'!$J$9),"") -> 41308.837 | G8: =IFERROR(-PPMT('Information Sheet'!$D$8/'Information Sheet'!$E$10,'Repayment Schedule'!C8,'Information Sheet'!$D$9*'Information Sheet'!$E$10,'Information Sheet'!$J$9),"") -> 159056.33 | H8: =IF(C8="","",-PMT('Information Sheet'!$D$8/'Information Sheet'!$E$10,'Information Sheet'!$D$9*'Information Sheet'!$E$10,'Information Sheet'!$J$9)) -> 200365.16
C9: =IF(C8<'Information Sheet'!$J$11,'Repayment Schedule'!C8+1,"") -> 4 | D9: =IFERROR(EDATE('Information Sheet'!$D$13,'Information Sheet'!$F$10*'Repayment Schedule'!C9),"") -> 45901 | E9: =IFERROR((E8-G9),"") -> 321888.46 | F9: =IFERROR(-IPMT('Information Sheet'!$D$8/'Information Sheet'!$E$10,'Repayment Schedule'!C9,'Information Sheet'!$D$9*'Information Sheet'!$E$10,'Information Sheet'!$J$9),"") -> 28584.331 | G9: =IFERROR(-PPMT('Information Sheet'!$D$8/'Information Sheet'!$E$10,'Repayment Schedule'!C9,'Information Sheet'!$D$9*'Information Sheet'!$E$10,'Information Sheet'!$J$9),"") -> 171780.83 | H9: =IF(C9="","",-PMT('Information Sheet'!$D$8/'Information Sheet'!$E$10,'Information Sheet'!$D$9*'Information Sheet'!$E$10,'Information Sheet'!$J$9)) -> 200365.16
C10: =IF(C9<'Information Sheet'!$J$11,'Repayment Schedule'!C9+1,"") -> 5 | D10: =IFERROR(EDATE('Information Sheet'!$D$13,'Information Sheet'!$F$10*'Repayment Schedule'!C10),"") -> 46266 | E10: =IFERROR((E9-G10),"") -> 136365.16 | F10: =IFERROR(-IPMT('Information Sheet'!$D$8/'Information Sheet'!$E$10,'Repayment Schedule'!C10,'Information Sheet'!$D$9*'Information Sheet'!$E$10,'Information Sheet'!$J$9),"") -> 14841.864 | G10: =IFERROR(-PPMT('Information Sheet'!$D$8/'Information Sheet'!$E$10,'Repayment Schedule'!C10,'Information Sheet'!$D$9*'Information Sheet'!$E$10,'Information Sheet'!$J$9),"") -> 185523.3 | H10: =IF(C10="","",-PMT('Information Sheet'!$D$8/'Information Sheet'!$E$10,'Information Sheet'!$D$9*'Information Sheet'!$E$10,'Information Sheet'!$J$9)) -> 200365.16
C11: =IF(C10<'Information Sheet'!$J$11,'Repayment Schedule'!C10+1,"") | D11: =IFERROR(EDATE('Information Sheet'!$D$13,'Information Sheet'!$F$10*'Repayment Schedule'!C11),"") | E11: =IFERROR((E10-G11),"") | F11: =IFERROR(-IPMT('Information Sheet'!$D$8/'Information Sheet'!$E$10,'Repayment Schedule'!C11,'Information Sheet'!$D$9*'Information Sheet'!$E$10,'Information Sheet'!$J$9),"") | G11: =IFERROR(-PPMT('Information Sheet'!$D$8/'Information Sheet'!$E$10,'Repayment Schedule'!C11,'Information Sheet'!$D$9*'Information Sheet'!$E$10,'Information Sheet'!$J$9),"") | H11: =IF(C11="","",-PMT('Information Sheet'!$D$8/'Information Sheet'!$E$10,'Information Sheet'!$D$9*'Information Sheet'!$E$10,'Information Sheet'!$J$9))
C12: =IF(C11<'Information Sheet'!$J$11,'Repayment Schedule'!C11+1,"") | D12: =IFERROR(EDATE('Information Sheet'!$D$13,'Information Sheet'!$F$10*'Repayment Schedule'!C12),"") | E12: =IFERROR((E11-G12),"") | F12: =IFERROR(-IPMT('Information Sheet'!$D$8/'Information Sheet'!$E$10,'Repayment Schedule'!C12,'Information Sheet'!$D$9*'Information Sheet'!$E$10,'Information Sheet'!$J$9),"") | G12: =IFERROR(-PPMT('Information Sheet'!$D$8/'Information Sheet'!$E$10,'Repayment Schedule'!C12,'Information Sheet'!$D$9*'Information Sheet'!$E$10,'Information Sheet'!$J$9),"") | H12: =IF(C12="","",-PMT('Information Sheet'!$D$8/'Information Sheet'!$E$10,'Information Sheet'!$D$9*'Information Sheet'!$E$10,'Information Sheet'!$J$9))
C13: =IF(C12<'Information Sheet'!$J$11,'Repayment Schedule'!C12+1,"") | D13: =IFERROR(EDATE('Information Sheet'!$D$13,'Information Sheet'!$F$10*'Repayment Schedule'!C13),"") | E13: =IFERROR((E12-G13),"") | F13: =IFERROR(-IPMT('Information Sheet'!$D$8/'Information Sheet'!$E$10,'Repayment Schedule'!C13,'Information Sheet'!$D$9*'Information Sheet'!$E$10,'Information Sheet'!$J$9),"") | G13: =IFERROR(-PPMT('Information Sheet'!$D$8/'Information Sheet'!$E$10,'Repayment Schedule'!C13,'Information Sheet'!$D$9*'Information Sheet'!$E$10,'Information Sheet'!$J$9),"") | H13: =IF(C13="","",-PMT('Information Sheet'!$D$8/'Information Sheet'!$E$10,'Information Sheet'!$D$9*'Information Sheet'!$E$10,'Information Sheet'!$J$9))
C14: =IF(C13<'Information Sheet'!$J$11,'Repayment Schedule'!C13+1,"") | D14: =IFERROR(EDATE('Information Sheet'!$D$13,'Information Sheet'!$F$10*'Repayment Schedule'!C14),"") | E14: =IFERROR((E13-G14),"") | F14: =IFERROR(-IPMT('Information Sheet'!$D$8/'Information Sheet'!$E$10,'Repayment Schedule'!C14,'Information Sheet'!$D$9*'Information Sheet'!$E$10,'Information Sheet'!$J$9),"") | G14: =IFERROR(-PPMT('Information Sheet'!$D$8/'Information Sheet'!$E$10,'Repayment Schedule'!C14,'Information Sheet'!$D$9*'Information Sheet'!$E$10,'Information Sheet'!$J$9),"") | H14: =IF(C14="","",-PMT('Information Sheet'!$D$8/'Information Sheet'!$E$10,'Information Sheet'!$D$9*'Information Sheet'!$E$10,'Information Sheet'!$J$9))
C15: =IF(C14<'Information Sheet'!$J$11,'Repayment Schedule'!C14+1,"") | D15: =IFERROR(EDATE('Information Sheet'!$D$13,'Information Sheet'!$F$10*'Repayment Schedule'!C15),"") | E15: =IFERROR((E14-G15),"") | F15: =IFERROR(-IPMT('Information Sheet'!$D$8/'Information Sheet'!$E$10,'Repayment Schedule'!C15,'Information Sheet'!$D$9*'Information Sheet'!$E$10,'Information Sheet'!$J$9),"") | G15: =IFERROR(-PPMT('Information Sheet'!$D$8/'Information Sheet'!$E$10,'Repayment Schedule'!C15,'Information Sheet'!$D$9*'Information Sheet'!$E$10,'Information Sheet'!$J$9),"") | H15: =IF(C15="","",-PMT('Information Sheet'!$D$8/'Information Sheet'!$E$10,'Information Sheet'!$D$9*'Information Sheet'!$E$10,'Information Sheet'!$J$9))
C16: =IF(C15<'Information Sheet'!$J$11,'Repayment Schedule'!C15+1,"") | D16: =IFERROR(EDATE('Information Sheet'!$D$13,'Information Sheet'!$F$10*'Repayment Schedule'!C16),"") | E16: =IFERROR((E15-G16),"") | F16: =IFERROR(-IPMT('Information Sheet'!$D$8/'Information Sheet'!$E$10,'Repayment Schedule'!C16,'Information Sheet'!$D$9*'Information Sheet'!$E$10,'Information Sheet'!$J$9),"") | G16: =IFERROR(-PPMT('Information Sheet'!$D$8/'Information Sheet'!$E$10,'Repayment Schedule'!C16,'Information Sheet'!$D$9*'Information Sheet'!$E$10,'Information Sheet'!$J$9),"") | H16: =IF(C16="","",-PMT('Information Sheet'!$D$8/'Information Sheet'!$E$10,'Information Sheet'!$D$9*'Information Sheet'!$E$10,'Information Sheet'!$J$9))
C17: =IF(C16<'Information Sheet'!$J$11,'Repayment Schedule'!C16+1,"") | D17: =IFERROR(EDATE('Information Sheet'!$D$13,'Information Sheet'!$F$10*'Repayment Schedule'!C17),"") | E17: =IFERROR((E16-G17),"") | F17: =IFERROR(-IPMT('Information Sheet'!$D$8/'Information Sheet'!$E$10,'Repayment Schedule'!C17,'Information Sheet'!$D$9*'Information Sheet'!$E$10,'Information Sheet'!$J$9),"") | G17: =IFERROR(-PPMT('Information Sheet'!$D$8/'Information Sheet'!$E$10,'Repayment Schedule'!C17,'Information Sheet'!$D$9*'Information Sheet'!$E$10,'Information Sheet'!$J$9),"") | H17: =IF(C17="","",-PMT('Information Sheet'!$D$8/'Information Sheet'!$E$10,'Information Sheet'!$D$9*'Information Sheet'!$E$10,'Information Sheet'!$J$9))
C18: =IF(C17<'Information Sheet'!$J$11,'Repayment Schedule'!C17+1,"") | D18: =IFERROR(EDATE('Information Sheet'!$D$13,'Information Sheet'!$F$10*'Repayment Schedule'!C18),"") | E18: =IFERROR((E17-G18),"") | F18: =IFERROR(-IPMT('Information Sheet'!$D$8/'Information Sheet'!$E$10,'Repayment Schedule'!C18,'Information Sheet'!$D$9*'Information Sheet'!$E$10,'Information Sheet'!$J$9),"") | G18: =IFERROR(-PPMT('Information Sheet'!$D$8/'Information Sheet'!$E$10,'Repayment Schedule'!C18,'Information Sheet'!$D$9*'Information Sheet'!$E$10,'Information Sheet'!$J$9),"") | H18: =IF(C18="","",-PMT('Information Sheet'!$D$8/'Information Sheet'!$E$10,'Information Sheet'!$D$9*'Information Sheet'!$E$10,'Information Sheet'!$J$9))
... C150: =IF(C149<'Information Sheet'!$J$11,'Repayment Schedule'!C149+1,"") | D150: =IFERROR(EDATE('Information Sheet'!$D$13,'Information Sheet'!$F$10*'Repayment Schedule'!C150),"") | E150: =IFERROR((E149-G150),"") | F150: =IFERROR(-IPMT('Information Sheet'!$D$8/'Information Sheet'!$E$10,'Repayment Schedule'!C150,'Information Sheet'!$D$9*'Information Sheet'!$E$10,'Information Sheet'!$J$9),"") | G150: =IFERROR(-PPMT('Information Sheet'!$D$8/'Information Sheet'!$E$10,'Repayment Schedule'!C150,'Information Sheet'!$D$9*'Information Sheet'!$E$10,'Information Sheet'!$J$9),"") | H150: =IF(C150="","",-PMT('Information Sheet'!$D$8/'Information Sheet'!$E$10,'Information Sheet'!$D$9*'Information Sheet'!$E$10,'Information Sheet'!$J$9))
C151: =IF(C150<'Information Sheet'!$J$11,'Repayment Schedule'!C150+1,"") | D151: =IFERROR(EDATE('Information Sheet'!$D$13,'Information Sheet'!$F$10*'Repayment Schedule'!C151),"") | E151: =IFERROR((E150-G151),"") | F151: =IF(C151="","",-IPMT('Information Sheet'!$D$8/'Information Sheet'!$E$10,'Repayment Schedule'!C151,'Information Sheet'!$D$9*'Information Sheet'!$E$10,'Information Sheet'!$J$9)) | G151: =IF(C151="","",-PPMT('Information Sheet'!$D$8/'Information Sheet'!$E$10,'Repayment Schedule'!C151,'Information Sheet'!$D$9*'Information Sheet'!$E$10,'Information Sheet'!$J$9)) | H151: =IF(C151="","",-PMT('Information Sheet'!$D$8/'Information Sheet'!$E$10,'Information Sheet'!$D$9*'Information Sheet'!$E$10,'Information Sheet'!$J$9))
C152: =IF(C151<'Information Sheet'!$J$11,'Repayment Schedule'!C151+1,"") | D152: =IFERROR(EDATE('Information Sheet'!$D$13,'Information Sheet'!$F$10*'Repayment Schedule'!C152),"") | E152: =IFERROR((E151-G152),"") | F152: =IF(C152="","",-IPMT('Information Sheet'!$D$8/'Information Sheet'!$E$10,'Repayment Schedule'!C152,'Information Sheet'!$D$9*'Information Sheet'!$E$10,'Information Sheet'!$J$9)) | G152: =IF(C152="","",-PPMT('Information Sheet'!$D$8/'Information Sheet'!$E$10,'Repayment Schedule'!C152,'Information Sheet'!$D$9*'Information Sheet'!$E$10,'Information Sheet'!$J$9)) | H152: =IF(C152="","",-PMT('Information Sheet'!$D$8/'Information Sheet'!$E$10,'Information Sheet'!$D$9*'Information Sheet'!$E$10,'Information Sheet'!$J$9))
C153: =IF(C152<'Information Sheet'!$J$11,'Repayment Schedule'!C152+1,"") | D153: =IFERROR(EDATE('Information Sheet'!$D$13,'Information Sheet'!$F$10*'Repayment Schedule'!C153),"") | E153: =IFERROR((E152-G153),"") | F153: =IF(C153="","",-IPMT('Information Sheet'!$D$8/'Information Sheet'!$E$10,'Repayment Schedule'!C153,'Information Sheet'!$D$9*'Information Sheet'!$E$10,'Information Sheet'!$J$9)) | G153: =IF(C153="","",-PPMT('Information Sheet'!$D$8/'Information Sheet'!$E$10,'Repayment Schedule'!C153,'Information Sheet'!$D$9*'Information Sheet'!$E$10,'Information Sheet'!$J$9)) | H153: =IF(C153="","",-PMT('Information Sheet'!$D$8/'Information Sheet'!$E$10,'Information Sheet'!$D$9*'Information Sheet'!$E$10,'Information Sheet'!$J$9))
C154: =IF(C153<'Information Sheet'!$J$11,'Repayment Schedule'!C153+1,"") | D154: =IFERROR(EDATE('Information Sheet'!$D$13,'Information Sheet'!$F$10*'Repayment Schedule'!C154),"") | E154: =IFERROR((E153-G154),"") | F154: =IF(C154="","",-IPMT('Information Sheet'!$D$8/'Information Sheet'!$E$10,'Repayment Schedule'!C154,'Information Sheet'!$D$9*'Information Sheet'!$E$10,'Information Sheet'!$J$9)) | G154: =IF(C154="","",-PPMT('Information Sheet'!$D$8/'Information Sheet'!$E$10,'Repayment Schedule'!C154,'Information Sheet'!$D$9*'Information Sheet'!$E$10,'Information Sheet'!$J$9)) | H154: =IF(C154="","",-PMT('Information Sheet'!$D$8/'Information Sheet'!$E$10,'Information Sheet'!$D$9*'Information Sheet'!$E$10,'Information Sheet'!$J$9))
C155: =IF(C154<'Information Sheet'!$J$11,'Repayment Schedule'!C154+1,"") | D155: =IFERROR(EDATE('Information Sheet'!$D$13,'Information Sheet'!$F$10*'Repayment Schedule'!C155),"") | E155: =IFERROR((E154-G155),"") | F155: =IF(C155="","",-IPMT('Information Sheet'!$D$8/'Information Sheet'!$E$10,'Repayment Schedule'!C155,'Information Sheet'!$D$9*'Information Sheet'!$E$10,'Information Sheet'!$J$9)) | G155: =IF(C155="","",-PPMT('Information Sheet'!$D$8/'Information Sheet'!$E$10,'Repayment Schedule'!C155,'Information Sheet'!$D$9*'Information Sheet'!$E$10,'Information Sheet'!$J$9)) | H155: =IF(C155="","",-PMT('Information Sheet'!$D$8/'Information Sheet'!$E$10,'Information Sheet'!$D$9*'Information Sheet'!$E$10,'Information Sheet'!$J$9))
C156: =IF(C155<'Information Sheet'!$J$11,'Repayment Schedule'!C155+1,"") | D156: =IFERROR(EDATE('Information Sheet'!$D$13,'Information Sheet'!$F$10*'Repayment Schedule'!C156),"") | E156: =IFERROR((E155-G156),"") | F156: =IF(C156="","",-IPMT('Information Sheet'!$D$8/'Information Sheet'!$E$10,'Repayment Schedule'!C156,'Information Sheet'!$D$9*'Information Sheet'!$E$10,'Information Sheet'!$J$9)) | G156: =IF(C156="","",-PPMT('Information Sheet'!$D$8/'Information Sheet'!$E$10,'Repayment Schedule'!C156,'Information Sheet'!$D$9*'Information Sheet'!$E$10,'Information Sheet'!$J$9)) | H156: =IF(C156="","",-PMT('Information Sheet'!$D$8/'Information Sheet'!$E$10,'Information Sheet'!$D$9*'Information Sheet'!$E$10,'Information Sheet'!$J$9))
C157: =IF(C156<'Information Sheet'!$J$11,'Repayment Schedule'!C156+1,"") | D157: =IFERROR(EDATE('Information Sheet'!$D$13,'Information Sheet'!$F$10*'Repayment Schedule'!C157),"") | E157: =IFERROR((E156-G157),"") | F157: =IF(C157="","",-IPMT('Information Sheet'!$D$8/'Information Sheet'!$E$10,'Repayment Schedule'!C157,'Information Sheet'!$D$9*'Information Sheet'!$E$10,'Information Sheet'!$J$9)) | G157: =IF(C157="","",-PPMT('Information Sheet'!$D$8/'Information Sheet'!$E$10,'Repayment Schedule'!C157,'Information Sheet'!$D$9*'Information Sheet'!$E$10,'Information Sheet'!$J$9)) | H157: =IF(C157="","",-PMT('Information Sheet'!$D$8/'Information Sheet'!$E$10,'Information Sheet'!$D$9*'Information Sheet'!$E$10,'Information Sheet'!$J$9))
C158: =IF(C157<'Information Sheet'!$J$11,'Repayment Schedule'!C157+1,"") | D158: =IFERROR(EDATE('Information Sheet'!$D$13,'Information Sheet'!$F$10*'Repayment Schedule'!C158),"") | E158: =IFERROR((E157-G158),"") | F158: =IF(C158="","",-IPMT('Information Sheet'!$D$8/'Information Sheet'!$E$10,'Repayment Schedule'!C158,'Information Sheet'!$D$9*'Information Sheet'!$E$10,'Information Sheet'!$J$9)) | G158: =IF(C158="","",-PPMT('Information Sheet'!$D$8/'Information Sheet'!$E$10,'Repayment Schedule'!C158,'Information Sheet'!$D$9*'Information Sheet'!$E$10,'Information Sheet'!$J$9)) | H158: =IF(C158="","",-PMT('Information Sheet'!$D$8/'Information Sheet'!$E$10,'Information Sheet'!$D$9*'Information Sheet'!$E$10,'Information Sheet'!$J$9))

Sheet Concept Note

Sheet Audit Report
A2: Sheet | B2: Errors | C2: Cells
A3: Dashboard | B3: {=SUM(IF(ISERROR(Dashboard!A1:L21),1))} -> 0 | C3: =_xlfn.FORMULATEXT(B3) -> {=SUM(IF(ISERROR(Dashboard!A1:L21),1))}
A4: Information Sheet | B4: {=SUM(IF(ISERROR('Information Sheet'!C4:K13),1,0))} -> 0 | C4: =_xlfn.FORMULATEXT(B4) -> {=SUM(IF(ISERROR('Information Sheet'!C4:K13),1,0))}
A5: Repayment Schedule | B5: {=SUM(IF(ISERROR('Repayment Schedule'!A1:I179),1,0))} -> 0 | C5: =_xlfn.FORMULATEXT(B5) -> {=SUM(IF(ISERROR('Repayment Schedule'!A1:I179),1,0))}
A6: Total | B6: =SUM(B3:B5) -> 0
